azure/mgmt/streamanalytics/__init__.py
azure/mgmt/streamanalytics/_configuration.py
azure/mgmt/streamanalytics/_patch.py
azure/mgmt/streamanalytics/_stream_analytics_management_client.py
azure/mgmt/streamanalytics/_vendor.py
azure/mgmt/streamanalytics/_version.py
azure/mgmt/streamanalytics/aio/__init__.py
azure/mgmt/streamanalytics/aio/_configuration.py
azure/mgmt/streamanalytics/aio/_patch.py
azure/mgmt/streamanalytics/aio/_stream_analytics_management_client.py
azure/mgmt/streamanalytics/aio/operations/__init__.py
azure/mgmt/streamanalytics/aio/operations/_clusters_operations.py
azure/mgmt/streamanalytics/aio/operations/_functions_operations.py
azure/mgmt/streamanalytics/aio/operations/_inputs_operations.py
azure/mgmt/streamanalytics/aio/operations/_operations.py
azure/mgmt/streamanalytics/aio/operations/_outputs_operations.py
azure/mgmt/streamanalytics/aio/operations/_private_endpoints_operations.py
azure/mgmt/streamanalytics/aio/operations/_streaming_jobs_operations.py
azure/mgmt/streamanalytics/aio/operations/_subscriptions_operations.py
azure/mgmt/streamanalytics/aio/operations/_transformations_operations.py
azure/mgmt/streamanalytics/models/__init__.py
azure/mgmt/streamanalytics/models/_models_py3.py
azure/mgmt/streamanalytics/models/_stream_analytics_management_client_enums.py
azure/mgmt/streamanalytics/operations/__init__.py
azure/mgmt/streamanalytics/operations/_clusters_operations.py
azure/mgmt/streamanalytics/operations/_functions_operations.py
azure/mgmt/streamanalytics/operations/_inputs_operations.py
azure/mgmt/streamanalytics/operations/_operations.py
azure/mgmt/streamanalytics/operations/_outputs_operations.py
azure/mgmt/streamanalytics/operations/_private_endpoints_operations.py
azure/mgmt/streamanalytics/operations/_streaming_jobs_operations.py
azure/mgmt/streamanalytics/operations/_subscriptions_operations.py
azure/mgmt/streamanalytics/operations/_transformations_operations.py
azure_mgmt_streamanalytics-1.0.0.dist-info/LICENSE
azure_mgmt_streamanalytics-1.0.0.dist-info/METADATA
azure_mgmt_streamanalytics-1.0.0.dist-info/WHEEL
azure_mgmt_streamanalytics-1.0.0.dist-info/top_level.txt
azure_mgmt_streamanalytics-1.0.0.dist-info/RECORD
